filerecords/__init__.py
filerecords/api/__init__.py
filerecords/api/base.py
filerecords/api/file_record.py
filerecords/api/registry.py
filerecords/api/settings.py
filerecords/api/utils.py
filerecords/cli/__init__.py
filerecords/cli/auxiliary.py
filerecords/cli/clear.py
filerecords/cli/comment.py
filerecords/cli/destroy.py
filerecords/cli/export.py
filerecords/cli/flag.py
filerecords/cli/init.py
filerecords/cli/list.py
filerecords/cli/list_local.py
filerecords/cli/lookup.py
filerecords/cli/main.py
filerecords/cli/move.py
filerecords/cli/read.py
filerecords/cli/remove.py
filerecords/cli/undo.py
filerecords-0.0.1.dist-info/LICENSE.md
filerecords-0.0.1.dist-info/METADATA
filerecords-0.0.1.dist-info/WHEEL
filerecords-0.0.1.dist-info/entry_points.txt
filerecords-0.0.1.dist-info/top_level.txt
filerecords-0.0.1.dist-info/RECORD
