Metadata-Version: 2.1
Name: filerecords
Version: 0.0.1
Summary: A command-line toolbox to keep file metadata in an organized and easily accessible way through comments and flags.
Home-page: https://github.com/NoahHenrikKleinschmidt/filerecords
Author: Noah H. Kleinschmidt
Author-email: noah.kleinschmidt@students.unibe.ch
Classifier: Programming Language :: Python :: 3
Classifier: License :: OSI Approved :: GNU General Public License v3 (GPLv3)
Classifier: Operating System :: OS Independent
Requires-Python: >=3.6
License-File: LICENSE.md
Requires-Dist: pandas
Requires-Dist: PyYAML
